<?xml version="1.0" encoding="utf-8"?><Search><pages Count="3"><page Index="1"><![CDATA[BACHELOR OF SCIENCE IN


             OFFICE ADMINISTRATION








                                LEVEL 1












                                        AREA III



                        CURRICULUM AND



                               INSTRUCTION]]></page><page Index="2"><![CDATA[CHED POLICIES

         AND STANDARDS]]></page><page Index="3"><![CDATA[Click the following to view the

                                          documents.




                  CMO NO. 19S. 2017]]></page></pages></Search>